{
  "opencollection": "1.0.0",
  "info": {
    "name": "FactSet Analytics Datastore API",
    "version": "1.0.0"
  },
  "request": {
    "auth": {
      "type": "basic",
      "username": "{{username}}",
      "password": "{{password}}"
    }
  },
  "items": [
    {
      "info": {
        "name": "Account",
        "type": "folder"
      },
      "items": [
        {
          "info": {
            "name": "Factset Redirects to the Raw Ppt/pdf Output Created by the Publisher Service.",
            "type": "http"
          },
          "http": {
            "method": "GET",
            "url": "https://api.factset.com/analytics/pub-datastore/swivel/v1/:document/:accountId/:date",
            "params": [
              {
                "name": "document",
                "value": "Analytics_Datastore",
                "type": "path",
                "description": "The Publisher document containing the report"
              },
              {
                "name": "accountId",
                "value": "LARGE_CORE",
                "type": "path",
                "description": "The account ID"
              },
              {
                "name": "date",
                "value": "2023-01-01",
                "type": "path",
                "description": "The as of date for the report"
              }
            ]
          },
          "docs": "Takes report parameter inputs and returns the object location for the specified report via a 302 redirect.\r\n\r\nNote: Due to Swagger UI functionality, the redirect is automatically followed when using 'Try it out', so instead of the 302 Header response, a 200 is returned with the Cargo response Body."
        },
        {
          "info": {
            "name": "Factset Redirects to the Underlying Pa/spar Data Represented in a Stach Format, With No as of Date Specified.",
            "type": "http"
          },
          "http": {
            "method": "GET",
            "url": "https://api.factset.com/analytics/pub-datastore/swivel/v1/:document/:assetName/:reportId/:tileId/:accountId",
            "params": [
              {
                "name": "document",
                "value": "Analytics_Datastore",
                "type": "path",
                "description": "The Publisher or Analytics Datafeed document containing the report"
              },
              {
                "name": "assetName",
                "value": "ADS_Demo.PA3",
                "type": "path",
                "description": "The PA/SPAR asset name and extension"
              },
              {
                "name": "reportId",
                "value": "report7",
                "type": "path",
                "description": "The PA/SPAR report ID"
              },
              {
                "name": "tileId",
                "value": "tile0",
                "type": "path",
                "description": "The PA/SPAR tile ID"
              },
              {
                "name": "accountId",
                "value": "LARGE_CORE",
                "type": "path",
                "description": "The account ID"
              }
            ]
          },
          "docs": "Takes report parameter inputs and returns the object location for the specified report via a 302 redirect.\r\n\r\nNote: Due to Swagger UI functionality, the redirect is automatically followed when using 'Try it out', so instead of the 302 Header response, a 200 is returned with the Cargo response Body."
        },
        {
          "info": {
            "name": "Factset Redirects to the Underlying Pa/spar Data Represented in a Stach Format.",
            "type": "http"
          },
          "http": {
            "method": "GET",
            "url": "https://api.factset.com/analytics/pub-datastore/swivel/v1/:document/:assetName/:reportId/:tileId/:accountId/:date",
            "params": [
              {
                "name": "document",
                "value": "Analytics_Datastore",
                "type": "path",
                "description": "The Publisher or Analytics Datafeed document containing the report"
              },
              {
                "name": "assetName",
                "value": "ADS_Demo.PA3",
                "type": "path",
                "description": "The PA/SPAR asset name and extension"
              },
              {
                "name": "reportId",
                "value": "report7",
                "type": "path",
                "description": "The PA/SPAR report ID"
              },
              {
                "name": "tileId",
                "value": "tile0",
                "type": "path",
                "description": "The PA/SPAR tile ID"
              },
              {
                "name": "accountId",
                "value": "LARGE_CORE",
                "type": "path",
                "description": "The account ID"
              },
              {
                "name": "date",
                "value": "2023-01-01",
                "type": "path",
                "description": "The as of date for the report"
              }
            ]
          },
          "docs": "Takes report parameter inputs and returns the object location for the specified report via a 302 redirect.\r\n\r\nNote: Due to Swagger UI functionality, the redirect is automatically followed when using 'Try it out', so instead of the 302 Header response, a 200 is returned with the Cargo response Body."
        },
        {
          "info": {
            "name": "Factset Redirects to the Underlying Insight/vault Data in a Stach Format.",
            "type": "http"
          },
          "http": {
            "method": "GET",
            "url": "https://api.factset.com/analytics/pub-datastore/swivel/v1/:document/:assetName/:reportId/:tileId/:accountId/:configId/:date",
            "params": [
              {
                "name": "document",
                "value": "Analytics_Datastore",
                "type": "path",
                "description": "The Analytics Datafeed document containing the report"
              },
              {
                "name": "assetName",
                "value": "ADS_Demo.PA3",
                "type": "path",
                "description": "The PA/SPAR asset name and extension"
              },
              {
                "name": "reportId",
                "value": "report7",
                "type": "path",
                "description": "The PA/SPAR report ID"
              },
              {
                "name": "tileId",
                "value": "tile0",
                "type": "path",
                "description": "The PA/SPAR tile ID"
              },
              {
                "name": "accountId",
                "value": "LARGE_CORE",
                "type": "path",
                "description": "The account ID"
              },
              {
                "name": "configId",
                "value": "acb5150d-4333-49e7-8e33-4f7fa749691e",
                "type": "path",
                "description": "The Vault configuration ID"
              },
              {
                "name": "date",
                "value": "2023-01-01",
                "type": "path",
                "description": "The as of date for the report"
              }
            ]
          },
          "docs": "The inclusion of a configId in the path indicates this is for Insight/Vault mappings only, as PA/SPAR mappings do not support the concept of configuration id.\r\n\r\nTakes report parameter inputs and returns the object location for the specified report via a 302 redirect.\r\n\r\nNote: Due to Swagger UI functionality, the redirect is automatically followed when using 'Try it out', so instead of the 302 Header response, a 200 is returned with the Cargo response Body."
        }
      ]
    },
    {
      "info": {
        "name": "Analytics",
        "type": "folder"
      },
      "items": [
        {
          "info": {
            "name": "Factset Gets an Object Given an Id. in This Case Id Retrieved From Mapping Location Header, Object Data in Response Body.",
            "type": "http"
          },
          "http": {
            "method": "GET",
            "url": "https://api.factset.com/analytics/pub-datastore/cargo/v1/groups/:groupId/objects/:objectId",
            "params": [
              {
                "name": "groupId",
                "value": "a4186c50f8e74f979d271dd22298c901",
                "type": "path",
                "description": "The ID of the group"
              },
              {
                "name": "objectId",
                "value": "fe875bc4150542dea6bc237663a01a0d",
                "type": "path",
                "description": "The ID of the object"
              }
            ]
          },
          "docs": "Raw object data can be found in the response body. This can be either the mapped PDF/PPT or STACH json, depending on the mapping. https://pages.github.factset.com/analytics-reporting/stachschema/#/ \r\n\nOptional request header \"accept-encoding\", with allowed values of \"br\" and \"gzip\". If accept-encoding is passed, the response is compressed."
        },
        {
          "info": {
            "name": "Factset Gets a List of Documents That a User Has Access To.",
            "type": "http"
          },
          "http": {
            "method": "POST",
            "url": "https://api.factset.com/analytics/pub-datastore/tag-search/v1/documents/search",
            "body": {
              "type": "json",
              "data": "{}"
            }
          },
          "docs": "Retrieves metadata around documents stored in the Analytics Datastore Service. Each Document will have a 'url' property which will act as a re-direct to the underlying document data\r\n\r\nThis end point supports pagination and filtering through the use of the request body listed below.\r\n\r\nTo discover what tags are available to filter on, see GET /tags and GET /tags/{name}/values to retrieve these filter values.\r\n\r\nSimilarly, to discover what product types are available to filter on, see POST /produ"
        },
        {
          "info": {
            "name": "Factset Gets a List of Tag Definitions for the User.",
            "type": "http"
          },
          "http": {
            "method": "GET",
            "url": "https://api.factset.com/analytics/pub-datastore/tag-search/v1/tags",
            "params": [
              {
                "name": "_paginationOffset",
                "value": "",
                "type": "query",
                "description": "The offset integer on where to begin paginating"
              },
              {
                "name": "_paginationLimit",
                "value": "",
                "type": "query",
                "description": "The limit of records to return when paginating"
              }
            ]
          },
          "docs": "Tag definitions consist of a name and a type. Use this end point to see a list of pre-existing tags that can be used to filter on the Documents end point."
        },
        {
          "info": {
            "name": "Factset Get a Single Tag Definition Based on Its Name",
            "type": "http"
          },
          "http": {
            "method": "GET",
            "url": "https://api.factset.com/analytics/pub-datastore/tag-search/v1/tags/:name",
            "params": [
              {
                "name": "name",
                "value": "",
                "type": "path",
                "description": "The name of the tag"
              }
            ]
          },
          "docs": "Retrieve a tag definition based on its name"
        },
        {
          "info": {
            "name": "Factset Gets a List of Tag Values for the Given Name",
            "type": "http"
          },
          "http": {
            "method": "POST",
            "url": "https://api.factset.com/analytics/pub-datastore/tag-search/v1/tags/:name/values",
            "params": [
              {
                "name": "name",
                "value": "",
                "type": "path",
                "description": "The name of the tag"
              }
            ],
            "body": {
              "type": "json",
              "data": "{}"
            }
          },
          "docs": "Returns a list of tag values depending on the name provided. Supports filtering on additional tag name value pairs, which operates as an 'AND' where the Document must have the tag name specified in the path AND the filtered parameter."
        },
        {
          "info": {
            "name": "Factset Gets a List of Product Types That a User Has Access To.",
            "type": "http"
          },
          "http": {
            "method": "POST",
            "url": "https://api.factset.com/analytics/pub-datastore/tag-search/v1/product-types/search",
            "body": {
              "type": "json",
              "data": "{}"
            }
          },
          "docs": "Retrieves a list of product types that have been specified across all documents the user has access to"
        }
      ]
    }
  ],
  "bundled": true
}