{
  "cashFlowAmounts": [],
  "cashFlowDates": [],
  "country": "example_value",
  "currency": "example_value",
  "issueName": "example_value",
  "parAmt": 42.5,
  "parentName": "example_value",
  "ratingFitch": "example_value",
  "ratingFitchDates": [],
  "ratingFitchValues": [],
  "ratingMoodysDates": [],
  "ratingMoodysValues": [],
  "ratingSpDates": [],
  "ratingSpValues": [],
  "secondaryToVendorFlag": true,
  "sector": "example_value",
  "sectorBarclay1": "example_value",
  "sectorBarclay2": "example_value",
  "sectorBarclay3": "example_value",
  "sectorBarclay4": "example_value",
  "sectorDef": "example_value",
  "sectorIndustry": "example_value",
  "sectorMain": "example_value",
  "sectorMerrill1": "example_value",
  "sectorMerrill2": "example_value",
  "sectorMerrill3": "example_value",
  "sectorMerrill4": "example_value",
  "sectorSubGroup": "example_value",
  "vendorCoverageDate": "example_value"
}